tudaesasII/__init__.py
tudaesasII/beam2d.py
tudaesasII/quad4r.py
tudaesasII/tria3planestrain.py
tudaesasII/tria3planestress.py
tudaesasII/tria3r.py
tudaesasII/truss2d.py
tudaesasII/truss2d_sparse.py
tudaesasII/utils.py
tudaesasII/version.py
tudaesasII-2024.2.data/data/LICENSE
tudaesasII-2024.2.data/data/README.md
tudaesasII-2024.2.dist-info/LICENSE
tudaesasII-2024.2.dist-info/METADATA
tudaesasII-2024.2.dist-info/WHEEL
tudaesasII-2024.2.dist-info/top_level.txt
tudaesasII-2024.2.dist-info/RECORD
