Metadata-Version: 2.1
Name: tudaesasII
Version: 2024.2
Summary: Python module related to the Master's course SASII at the faculty of Aeropsace Engineering, TU Delft
Home-page: https://github.com/saullocastro/tudaesasII
Author: Saullo G. P. Castro, Jurij Sodja
Author-email: S.G.P.Castro@tudelft.nl, J.Sodja@tudelft.nl
License: 3-Clause BSD
Keywords: structural analysis vibration dynamics finite elements
Classifier: Development Status :: 6 - Mature
Classifier: Intended Audience :: Education
Classifier: Intended Audience :: Science/Research
Classifier: Intended Audience :: Developers
Classifier: Topic :: Scientific/Engineering
Classifier: Topic :: Scientific/Engineering :: Mathematics
Classifier: Topic :: Education
Classifier: Topic :: Software Development
Classifier: Topic :: Software Development :: Libraries :: Python Modules
Classifier: Operating System :: Microsoft :: Windows
Classifier: Operating System :: Unix
Classifier: Operating System :: POSIX :: BSD
Classifier: Programming Language :: Python :: 3.8
Classifier: Programming Language :: Python :: 3.9
Classifier: Programming Language :: Python :: 3.10
Classifier: Programming Language :: Python :: 3.11
Classifier: Programming Language :: Python :: 3.12
Classifier: License :: OSI Approved :: BSD License
License-File: LICENSE
Requires-Dist: numpy
Requires-Dist: scipy
Requires-Dist: structsolve
Requires-Dist: composites >=0.5.4
